divergent_thinking_mcp/__init__.py
divergent_thinking_mcp/constants.py
divergent_thinking_mcp/creativity_algorithms.py
divergent_thinking_mcp/divergent_mcp.py
divergent_thinking_mcp/enhanced_prompts.py
divergent_thinking_mcp/exceptions.py
divergent_thinking_mcp/mcp_utils.py
divergent_thinking_mcp/tool_definitions.py
divergent_thinking_mcp/validators.py
divergent_thinking_mcp-0.2.2.dist-info/METADATA
divergent_thinking_mcp-0.2.2.dist-info/WHEEL
divergent_thinking_mcp-0.2.2.dist-info/entry_points.txt
divergent_thinking_mcp-0.2.2.dist-info/licenses/LICENSE
divergent_thinking_mcp-0.2.2.dist-info/RECORD
