Metadata-Version: 2.4
Name: divergent-thinking-mcp
Version: 0.2.2
Summary: MCP server for divergent thinking
Project-URL: Homepage, https://github.com/Fridayxiao/divergent-thinking-mcp
Project-URL: Repository, https://github.com/Fridayxiao/divergent-thinking-mcp
Project-URL: Issues, https://github.com/Fridayxiao/divergent-thinking-mcp/issues
Author-email: Fridayxiao <bonjj84@gmail.com>
License: MIT
License-File: LICENSE
Keywords: ai,creativity,divergent-thinking,mcp,tool
Classifier: Development Status :: 4 - Beta
Classifier: Environment :: Console
Classifier: Intended Audience :: Developers
Classifier: License :: OSI Approved :: MIT License
Classifier: Programming Language :: Python :: 3.12
Classifier: Topic :: Scientific/Engineering :: Artificial Intelligence
Classifier: Topic :: Software Development :: Libraries :: Python Modules
Requires-Python: >=3.12
Requires-Dist: jinja2
Requires-Dist: mcp
Requires-Dist: pytest>=8.4.1
Provides-Extra: dev
Requires-Dist: black>=23.0.0; extra == 'dev'
Requires-Dist: flake8>=6.0.0; extra == 'dev'
Requires-Dist: mypy>=1.0.0; extra == 'dev'
Requires-Dist: pytest-asyncio>=0.21.0; extra == 'dev'
Requires-Dist: pytest>=7.0.0; extra == 'dev'
